Metadata-Version: 2.1
Name: vz-logger
Version: 0.1.0
Summary: Send beautiful messages to the Vizstack Logger.
Home-page: https://github.com/vizstack/vz-logger
Author: Ryan Holmdahl & Nikhil Bhattasali
Author-email: vizstack@gmail.com
License: MIT
Platform: UNKNOWN
